[
  {
    "filing_id": "0DEBFNG0000000000000000002",
    "politician_id": "0DEBMBR0000000000000000002",
    "regime_id": "0DEBREG0000000000000000001",
    "instrument_id": null,
    "asset_description_raw": "Freistaat Bayern, München — Beamter, Rückkehrrecht",
    "record_type": "interest",
    "asset_class": "other",
    "side": null,
    "transaction_date": null,
    "as_of_date": null,
    "notified_date": null,
    "value": null,
    "owner": "self",
    "extraction_confidence": 1.0,
    "extracted_by": "de_bundestag/html@1",
    "fingerprint": null,
    "details": {
      "mdb_id": 1049272,
      "wahlperiode": 21,
      "category_number": 1,
      "category_name": "Berufliche Tätigkeit vor der Mitgliedschaft im Deutschen Bundestag",
      "row_ordinal": 1,
      "entry_text": "Freistaat Bayern, München — Beamter, Rückkehrrecht",
      "amount_raw": null,
      "period": null,
      "amount_year": null,
      "partner": null,
      "profit_before_tax": false,
      "non_quantifiable": false,
      "ehrenamtlich": false,
      "language": "de",
      "value_source": "none"
    }
  },
  {
    "filing_id": "0DEBFNG0000000000000000002",
    "politician_id": "0DEBMBR0000000000000000002",
    "regime_id": "0DEBREG0000000000000000001",
    "instrument_id": null,
    "asset_description_raw": "Festspielhaus Management GmbH, Füssen — Mitglied des Kuratoriums des Festspielhauses Neuschwanstein",
    "record_type": "interest",
    "asset_class": "other",
    "side": null,
    "transaction_date": null,
    "as_of_date": null,
    "notified_date": null,
    "value": null,
    "owner": "self",
    "extraction_confidence": 1.0,
    "extracted_by": "de_bundestag/html@1",
    "fingerprint": null,
    "details": {
      "mdb_id": 1049272,
      "wahlperiode": 21,
      "category_number": 3,
      "category_name": "Funktionen in Unternehmen",
      "row_ordinal": 2,
      "entry_text": "Festspielhaus Management GmbH, Füssen — Mitglied des Kuratoriums des Festspielhauses Neuschwanstein",
      "amount_raw": null,
      "period": null,
      "amount_year": null,
      "partner": null,
      "profit_before_tax": false,
      "non_quantifiable": false,
      "ehrenamtlich": false,
      "language": "de",
      "value_source": "none"
    }
  },
  {
    "filing_id": "0DEBFNG0000000000000000002",
    "politician_id": "0DEBMBR0000000000000000002",
    "regime_id": "0DEBREG0000000000000000001",
    "instrument_id": null,
    "asset_description_raw": "Siebendächer Baugenossenschaft eG, Memmingen — Mitglied des Aufsichtsrates",
    "record_type": "interest",
    "asset_class": "other",
    "side": null,
    "transaction_date": null,
    "as_of_date": null,
    "notified_date": null,
    "value": {
      "low": "300.00",
      "high": "300.00",
      "currency": "EUR"
    },
    "owner": "self",
    "extraction_confidence": 1.0,
    "extracted_by": "de_bundestag/html@1",
    "fingerprint": null,
    "details": {
      "mdb_id": 1049272,
      "wahlperiode": 21,
      "category_number": 3,
      "category_name": "Funktionen in Unternehmen",
      "row_ordinal": 3,
      "entry_text": "Siebendächer Baugenossenschaft eG, Memmingen — Mitglied des Aufsichtsrates",
      "amount_raw": "monatlich, 300,00 EUR, Brutto; zuzüglich Summe unregelmäßiger Zahlungen 2025: 89,55 EUR, Brutto",
      "period": "monthly",
      "amount_year": null,
      "partner": null,
      "profit_before_tax": false,
      "non_quantifiable": false,
      "ehrenamtlich": false,
      "language": "de",
      "value_source": "betragsgenau"
    }
  },
  {
    "filing_id": "0DEBFNG0000000000000000002",
    "politician_id": "0DEBMBR0000000000000000002",
    "regime_id": "0DEBREG0000000000000000001",
    "instrument_id": null,
    "asset_description_raw": "Siebendächer Wohnbau-, Betreuungs- und Verwaltungsgesellschaft mbH, Memmingen — Mitglied des Aufsichtsrates",
    "record_type": "interest",
    "asset_class": "other",
    "side": null,
    "transaction_date": null,
    "as_of_date": null,
    "notified_date": null,
    "value": null,
    "owner": "self",
    "extraction_confidence": 1.0,
    "extracted_by": "de_bundestag/html@1",
    "fingerprint": null,
    "details": {
      "mdb_id": 1049272,
      "wahlperiode": 21,
      "category_number": 3,
      "category_name": "Funktionen in Unternehmen",
      "row_ordinal": 4,
      "entry_text": "Siebendächer Wohnbau-, Betreuungs- und Verwaltungsgesellschaft mbH, Memmingen — Mitglied des Aufsichtsrates",
      "amount_raw": null,
      "period": null,
      "amount_year": null,
      "partner": null,
      "profit_before_tax": false,
      "non_quantifiable": false,
      "ehrenamtlich": false,
      "language": "de",
      "value_source": "none"
    }
  },
  {
    "filing_id": "0DEBFNG0000000000000000002",
    "politician_id": "0DEBMBR0000000000000000002",
    "regime_id": "0DEBREG0000000000000000001",
    "instrument_id": null,
    "asset_description_raw": "Stadt Kaufbeuren, Kaufbeuren — Mitglied des Stadtrates",
    "record_type": "interest",
    "asset_class": "other",
    "side": null,
    "transaction_date": null,
    "as_of_date": null,
    "notified_date": null,
    "value": {
      "low": "508.00",
      "high": "508.00",
      "currency": "EUR"
    },
    "owner": "self",
    "extraction_confidence": 1.0,
    "extracted_by": "de_bundestag/html@1",
    "fingerprint": null,
    "details": {
      "mdb_id": 1049272,
      "wahlperiode": 21,
      "category_number": 4,
      "category_name": "Funktionen in Körperschaften und Anstalten des öffentlichen Rechts",
      "row_ordinal": 5,
      "entry_text": "Stadt Kaufbeuren, Kaufbeuren — Mitglied des Stadtrates",
      "amount_raw": "monatlich, 508,00 EUR, Brutto; zuzüglich Summe unregelmäßiger Zahlungen 2025: 140,00 EUR, Brutto; zuzüglich Summe unregelmäßiger Zahlungen 2026: 70,00 EUR, Brutto",
      "period": "monthly",
      "amount_year": null,
      "partner": null,
      "profit_before_tax": false,
      "non_quantifiable": false,
      "ehrenamtlich": false,
      "language": "de",
      "value_source": "betragsgenau"
    }
  },
  {
    "filing_id": "0DEBFNG0000000000000000002",
    "politician_id": "0DEBMBR0000000000000000002",
    "regime_id": "0DEBREG0000000000000000001",
    "instrument_id": null,
    "asset_description_raw": "Bundesstiftung Bauakademie, Berlin — Stellv. Mitglied des Stiftungsrates, ehrenamtlich (ab 25.09.2025)",
    "record_type": "interest",
    "asset_class": "other",
    "side": null,
    "transaction_date": null,
    "as_of_date": null,
    "notified_date": null,
    "value": null,
    "owner": "self",
    "extraction_confidence": 1.0,
    "extracted_by": "de_bundestag/html@1",
    "fingerprint": null,
    "details": {
      "mdb_id": 1049272,
      "wahlperiode": 21,
      "category_number": 5,
      "category_name": "Funktionen in Vereinen, Verbänden und Stiftungen",
      "row_ordinal": 6,
      "entry_text": "Bundesstiftung Bauakademie, Berlin — Stellv. Mitglied des Stiftungsrates, ehrenamtlich (ab 25.09.2025)",
      "amount_raw": null,
      "period": null,
      "amount_year": null,
      "partner": null,
      "profit_before_tax": false,
      "non_quantifiable": false,
      "ehrenamtlich": true,
      "language": "de",
      "value_source": "none"
    }
  },
  {
    "filing_id": "0DEBFNG0000000000000000002",
    "politician_id": "0DEBMBR0000000000000000002",
    "regime_id": "0DEBREG0000000000000000001",
    "instrument_id": null,
    "asset_description_raw": "Deutsche Renten Information e.V., Frankfurt/Main — Mitglied des Beirates, ehrenamtlich",
    "record_type": "interest",
    "asset_class": "other",
    "side": null,
    "transaction_date": null,
    "as_of_date": null,
    "notified_date": null,
    "value": null,
    "owner": "self",
    "extraction_confidence": 1.0,
    "extracted_by": "de_bundestag/html@1",
    "fingerprint": null,
    "details": {
      "mdb_id": 1049272,
      "wahlperiode": 21,
      "category_number": 5,
      "category_name": "Funktionen in Vereinen, Verbänden und Stiftungen",
      "row_ordinal": 7,
      "entry_text": "Deutsche Renten Information e.V., Frankfurt/Main — Mitglied des Beirates, ehrenamtlich",
      "amount_raw": null,
      "period": null,
      "amount_year": null,
      "partner": null,
      "profit_before_tax": false,
      "non_quantifiable": false,
      "ehrenamtlich": true,
      "language": "de",
      "value_source": "none"
    }
  },
  {
    "filing_id": "0DEBFNG0000000000000000002",
    "politician_id": "0DEBMBR0000000000000000002",
    "regime_id": "0DEBREG0000000000000000001",
    "instrument_id": null,
    "asset_description_raw": "Kneipp-Bund e.V., Bad Wörishofen — Mitglied des Expertenrates des Präsidiums, ehrenamtlich",
    "record_type": "interest",
    "asset_class": "other",
    "side": null,
    "transaction_date": null,
    "as_of_date": null,
    "notified_date": null,
    "value": null,
    "owner": "self",
    "extraction_confidence": 1.0,
    "extracted_by": "de_bundestag/html@1",
    "fingerprint": null,
    "details": {
      "mdb_id": 1049272,
      "wahlperiode": 21,
      "category_number": 5,
      "category_name": "Funktionen in Vereinen, Verbänden und Stiftungen",
      "row_ordinal": 8,
      "entry_text": "Kneipp-Bund e.V., Bad Wörishofen — Mitglied des Expertenrates des Präsidiums, ehrenamtlich",
      "amount_raw": null,
      "period": null,
      "amount_year": null,
      "partner": null,
      "profit_before_tax": false,
      "non_quantifiable": false,
      "ehrenamtlich": true,
      "language": "de",
      "value_source": "none"
    }
  },
  {
    "filing_id": "0DEBFNG0000000000000000002",
    "politician_id": "0DEBMBR0000000000000000002",
    "regime_id": "0DEBREG0000000000000000001",
    "instrument_id": null,
    "asset_description_raw": "Landesvereinigung der Helfer und Förderer des Technischen Hilfswerks in Bayern e.V., München — Landesvorsitzender, ehrenamtlich",
    "record_type": "interest",
    "asset_class": "other",
    "side": null,
    "transaction_date": null,
    "as_of_date": null,
    "notified_date": null,
    "value": null,
    "owner": "self",
    "extraction_confidence": 1.0,
    "extracted_by": "de_bundestag/html@1",
    "fingerprint": null,
    "details": {
      "mdb_id": 1049272,
      "wahlperiode": 21,
      "category_number": 5,
      "category_name": "Funktionen in Vereinen, Verbänden und Stiftungen",
      "row_ordinal": 9,
      "entry_text": "Landesvereinigung der Helfer und Förderer des Technischen Hilfswerks in Bayern e.V., München — Landesvorsitzender, ehrenamtlich",
      "amount_raw": null,
      "period": null,
      "amount_year": null,
      "partner": null,
      "profit_before_tax": false,
      "non_quantifiable": false,
      "ehrenamtlich": true,
      "language": "de",
      "value_source": "none"
    }
  },
  {
    "filing_id": "0DEBFNG0000000000000000002",
    "politician_id": "0DEBMBR0000000000000000002",
    "regime_id": "0DEBREG0000000000000000001",
    "instrument_id": null,
    "asset_description_raw": "Outward Bound Deutschland - e.V., Schwangau — Mitglied des Vorstandes, ehrenamtlich",
    "record_type": "interest",
    "asset_class": "other",
    "side": null,
    "transaction_date": null,
    "as_of_date": null,
    "notified_date": null,
    "value": null,
    "owner": "self",
    "extraction_confidence": 1.0,
    "extracted_by": "de_bundestag/html@1",
    "fingerprint": null,
    "details": {
      "mdb_id": 1049272,
      "wahlperiode": 21,
      "category_number": 5,
      "category_name": "Funktionen in Vereinen, Verbänden und Stiftungen",
      "row_ordinal": 10,
      "entry_text": "Outward Bound Deutschland - e.V., Schwangau — Mitglied des Vorstandes, ehrenamtlich",
      "amount_raw": null,
      "period": null,
      "amount_year": null,
      "partner": null,
      "profit_before_tax": false,
      "non_quantifiable": false,
      "ehrenamtlich": true,
      "language": "de",
      "value_source": "none"
    }
  },
  {
    "filing_id": "0DEBFNG0000000000000000002",
    "politician_id": "0DEBMBR0000000000000000002",
    "regime_id": "0DEBREG0000000000000000001",
    "instrument_id": null,
    "asset_description_raw": "Stiftung Technisches Hilfswerk (THW), Berlin — Mitglied des Kuratoriums, ehrenamtlich",
    "record_type": "interest",
    "asset_class": "other",
    "side": null,
    "transaction_date": null,
    "as_of_date": null,
    "notified_date": null,
    "value": null,
    "owner": "self",
    "extraction_confidence": 1.0,
    "extracted_by": "de_bundestag/html@1",
    "fingerprint": null,
    "details": {
      "mdb_id": 1049272,
      "wahlperiode": 21,
      "category_number": 5,
      "category_name": "Funktionen in Vereinen, Verbänden und Stiftungen",
      "row_ordinal": 11,
      "entry_text": "Stiftung Technisches Hilfswerk (THW), Berlin — Mitglied des Kuratoriums, ehrenamtlich",
      "amount_raw": null,
      "period": null,
      "amount_year": null,
      "partner": null,
      "profit_before_tax": false,
      "non_quantifiable": false,
      "ehrenamtlich": true,
      "language": "de",
      "value_source": "none"
    }
  },
  {
    "filing_id": "0DEBFNG0000000000000000002",
    "politician_id": "0DEBMBR0000000000000000002",
    "regime_id": "0DEBREG0000000000000000001",
    "instrument_id": null,
    "asset_description_raw": "THW-Bundesvereinigung e.V. (THW-BV), Berlin — Mitglied des Präsidiums, ehrenamtlich",
    "record_type": "interest",
    "asset_class": "other",
    "side": null,
    "transaction_date": null,
    "as_of_date": null,
    "notified_date": null,
    "value": null,
    "owner": "self",
    "extraction_confidence": 1.0,
    "extracted_by": "de_bundestag/html@1",
    "fingerprint": null,
    "details": {
      "mdb_id": 1049272,
      "wahlperiode": 21,
      "category_number": 5,
      "category_name": "Funktionen in Vereinen, Verbänden und Stiftungen",
      "row_ordinal": 12,
      "entry_text": "THW-Bundesvereinigung e.V. (THW-BV), Berlin — Mitglied des Präsidiums, ehrenamtlich",
      "amount_raw": null,
      "period": null,
      "amount_year": null,
      "partner": null,
      "profit_before_tax": false,
      "non_quantifiable": false,
      "ehrenamtlich": true,
      "language": "de",
      "value_source": "none"
    }
  }
]
